pynomials/__init__.py
pynomials-0.0.5.dist-info/LICENSE.txt
pynomials-0.0.5.dist-info/METADATA
pynomials-0.0.5.dist-info/WHEEL
pynomials-0.0.5.dist-info/top_level.txt
pynomials-0.0.5.dist-info/RECORD
