Metadata-Version: 2.1
Name: pynomials
Version: 0.0.5
Summary: provides mathematical Polynomials as Python objects
Home-page: https://github.com/divyajeettt/pynomials
Author: Divyajeet Singh
Author-email: knightt1821@gmail.com
Classifier: Programming Language :: Python :: 3
Classifier: License :: OSI Approved :: MIT License
Classifier: Operating System :: OS Independent
License-File: LICENSE.txt
Requires-Dist: matplotlib
Requires-Dist: numpy
